MATLAB/__init__.py
MATLAB/num.py
MATLAB/plots.py
MATLAB/sym.py
pyMATLABstyle-1.2.1.dist-info/METADATA
pyMATLABstyle-1.2.1.dist-info/WHEEL
pyMATLABstyle-1.2.1.dist-info/top_level.txt
pyMATLABstyle-1.2.1.dist-info/RECORD
