Metadata-Version: 2.1
Name: pyMATLABstyle
Version: 1.2.1
Summary: MATLAB style of creating numpy/sympy matrices, and a few MATLAB style functions
Home-page: https://github.com/the0demiurge/pyMATLAB-style
Author: Charles Xu
Author-email: charl3s.xu@gmail.com
License: UNKNOWN
Platform: UNKNOWN
Classifier: Programming Language :: Python
Classifier: License :: Other/Proprietary License
Classifier: Operating System :: Android
Classifier: Operating System :: iOS
Classifier: Operating System :: MacOS
Classifier: Operating System :: Microsoft
Classifier: Operating System :: Other OS
Classifier: Operating System :: POSIX
Classifier: Operating System :: Unix
Requires-Dist: numpy
Requires-Dist: sympy
Requires-Dist: matplotlib
